sra added/s2.v
module pc (
    input [31:0] PCNext,
    input clk,
    output reg [31:0] PC_cur
);
    initial PC_cur =32'h00000000;

always @(posedge clk)
begin
    PC_cur <= PCNext;
end
endmodule

module instr_mem (
    input [31:0] addr_instr,
    output reg [31:0] rd_instr
);
reg [31:0] mem [31:0];
initial begin
    mem[0]=32'h00300093;
    mem[1]=32'h00508113;
    mem[2]=32'h40110233;
    mem[3]=32'h0040e2b3;
    mem[4]=32'h0050a423;
    mem[5]=32'h0080a183;
    mem[6]=32'h00518333;
    mem[7]=32'h002303b3;
    mem[8]=32'h0063f1b3;
    mem[9]=32'h00529463;
    mem[10]=32'h00518333;
    mem[11]=32'h00219463;
    mem[12]=32'h00612433;
    mem[13]=32'h00a3e213;
    mem[14]=32'h01127193;
    mem[15]=32'h01d22493;
    
    mem[16]=32'h00200593;   // addi x11,x0,2
    mem[17]=32'h00e58613;   // addi x12,x11,14
    mem[18]=32'h40b656b3;   // sra x13,x12,x11
    mem[19]=32'hff000713;   // addi x14,x0,-16
    mem[20]=32'h40d757b3;   // sra x15,x14,x13
    
    mem[21]=32'hfadff56f;
    
    /*addi x1,x0,3
    addi x2,x1,5
    sub x4,x2,x1
    or x5,x1,x4
    sw x5, 8(x1)
    lw x3, 8(x1)
    add x6,x3,x5
    add x7,x6,x2
    and x3,x7,x6
    beq x5,x5,8
    beq x3,x2,8
    slt x8,x2,x6
    ori x4,x7,10
    andi x3,x4,17
    slti x9,x4,29
    jal x10,4*/

end
always @ (addr_instr) begin
    rd_instr = mem[addr_instr[31:2]];
end
endmodule

module main_decoder(
    input [6:0] op,
    input [2:0] funct3,
    input funct7_5,
    output branch,
    output jump,
    output MemWrite,
    output ALUSrc,
    output [1:0] ImmSrc,
    output RegWrite,
    output [1:0] ALUOp,
    output [1:0] ResultSrc,
    output SraSrc);

reg [11:0] controls;

always @(*)
begin
    case (op)
        7'b0000011: controls <= 12'b010010010000; // lw
        7'b0100011: controls <= 12'b000111xx0000; // sw
        7'b0110011: begin
            controls <= 12'b01xx00000100; // R-type
            case (funct3)
                3'b101: begin
                    case (funct7_5)
                        1'b1: controls[11] <= 1'b1;
                        default: controls[11] <= 1'b0;
                    endcase
                end
                default: controls[11] <= 1'b0;
            endcase
        end
        7'b1100011: controls <= 12'b001000xx1010; // beq

        7'b0010011: controls <= 12'b010010000100; // I-type
        7'b1101111: controls <= 12'b0111x0100xx1; // jal
        default: controls <= 12'bxxxxxxxxxxxx; // undefined
    endcase
end

assign SraSrc = controls[11];
assign RegWrite = controls[10];
assign ImmSrc = controls[9:8];
assign ALUSrc = controls[7];
assign MemWrite = controls[6];
assign ResultSrc = controls[5:4];
assign branch = controls[3];
assign ALUOp = controls[2:1];
assign jump = controls[0];
endmodule

module ALU_Decoder(
    input op5, funct7_5,
    input [2:0] funct3,
    input [1:0] ALUOp,
    output reg [2:0] ALUControl
);

always @(*) begin
    case(ALUOp)
        2'b00: ALUControl = 3'b000; // add
        2'b01: ALUControl = 3'b001; // sub
        default: begin
            case(funct3)
                3'b000: begin
                    if (op5 & funct7_5) begin
                        ALUControl = 3'b001; // sub
                    end else begin
                        ALUControl = 3'b000; // add
                    end
                end
                3'b010: ALUControl = 3'b101; // slt
                3'b110: ALUControl = 3'b011; // or
                3'b111: ALUControl = 3'b010; // and
                default: ALUControl = 3'bxxx; 
            endcase
        end
    endcase
end
endmodule

module control_unit(
    input [6:0] op,
    input [2:0] funct3,
    input funct7_5,
    input Zero,
    
    output PCSrc,
    output [1:0] ResultSrc,
    output MemWrite,
    output [2:0] ALUControl,
    output ALUSrc,
    output [1:0] ImmSrc,
    output RegWrite,
    output SraSrc);

wire branch, jump;
wire [1:0] ALUOp;


main_decoder main_dec (op,funct3,funct7_5,branch,jump,MemWrite,ALUSrc,ImmSrc,RegWrite,ALUOp,ResultSrc,SraSrc);
ALU_Decoder ALU_dec (op[5],funct7_5,funct3,ALUOp,ALUControl);

assign PCSrc = (branch & Zero) | jump;

endmodule

module reg_file(
    input [4:0] R1,
    input [4:0] R2,
    input [4:0] W1,
    input [31:0] WD1,
    input RegWrite,
    input clk,
    output [31:0] RD1,
    output [31:0] RD2
);
reg [31:0] Registers [31:0]; 

integer i;
initial begin
    for (i = 0; i < 32; i = i + 1) begin
        Registers[i] = 32'h00000000;
    end
end

always @(posedge clk) begin
    if (W1 != 5'b00000 && RegWrite) begin
        Registers[W1] <= WD1;
    end
end
assign RD1 = Registers[R1];
assign RD2 = Registers[R2];
endmodule

module extend(
    input [1:0] ImmSrc,
    input [31:7] instruction,
    output reg [31:0] ImmExt
);

always @* begin
    case (ImmSrc)
        // I-Type
        2'b00: ImmExt = { {20{instruction[31]}}, instruction[31:20] };
        // S-Type
        2'b01: ImmExt = { {20{instruction[31]}}, instruction[31:25], instruction[11:7] };
        // B-Type
        2'b10: ImmExt = { {20{instruction[31]}}, instruction[7], instruction[30:25], instruction[11:8], 1'b0 };
        // J-Type(jal)
        2'b11: ImmExt = { {12{instruction[31]}}, instruction[19:12], instruction[20], instruction[30:21], 1'b0 };
        default: ImmExt = 32'hxxxxxxxx;
    endcase
end
endmodule

module mux_2x1(
    input [31:0] data0,  
    input [31:0] data1,  
    input sel,            
    output [31:0] out 
);
assign out = sel ? data1 : data0;
endmodule

module ALU(
    input [31:0] SrcA,
    input [31:0] SrcB,
    input [2:0] ALUControl,
    output Zero,
    output reg [31:0] ALUResult
);
//reg [31:0] alu_res;
always @* begin
    case (ALUControl)
        // add
        3'b000: ALUResult = SrcA + SrcB;
        // sub
        3'b001: ALUResult = SrcA - SrcB;
        // and
        3'b010: ALUResult = SrcA & SrcB;
        // or
        3'b011: ALUResult = SrcA | SrcB;
        // slt
        3'b101: ALUResult = (SrcA < SrcB) ? 32'h00000001 : 32'h00000000;
        default: ALUResult = 32'hxxxxxxxx;
    endcase
end
assign Zero = (ALUResult == 32'h00000000) ? 1'b1 : 1'b0;
//assign ALUResult = alu_res;
endmodule

module data_memr(
    input [31:0] a_enter,
    input [31:0] write_data,
    input clk,
    input write_en,
    output [31:0] read_data
);
reg [31:0] datamem [63:0];
integer i;
initial begin
    for (i = 0; i < 64; i = i + 1) begin
        datamem[i] = 32'h00000000;
    end
end

always @(posedge clk) begin
    if (write_en) begin
        datamem[a_enter] <= write_data;
    end
end
assign read_data = datamem[a_enter];
endmodule

module mux_3(
    input [31:0] a,
    input [31:0] b,
    input [31:0] c,
    input [1:0] sel,
    output reg [31:0] y
);

always @* begin
    case(sel)
        2'b00: y = a;
        2'b01: y = b;
        2'b10: y = c;
        default: y = 32'hxxxxxxxx;
    endcase
end
endmodule

module adder_jal(
input [31:0] PC,
output [31:0] PCPlus4);

assign PCPlus4 = PC + 4;
endmodule

module adder_branch(
input [31:0] PC,
input [31:0] ImmExt,
output [31:0] PCTarget);

assign PCTarget = PC + ImmExt;
endmodule

module shift_right_arithmetic (
    input signed[31:0] data_in,
    input [4:0] shift_amount,
    output reg [31:0] result
);

always @* begin
     result <= data_in >>> shift_amount;
end

endmodule

module asd(
    input clk,
    input reset,
    output [31:0] pc,
    output [31:0] instr,
    output Zero,
    output PCSrc,
    output [1:0] ResultSrc,
    output MemWrite,
    output [2:0] ALUControl,
    output ALUSrc,
    output [1:0] ImmSrc,
    output RegWrite,
    output [31:0] resultwd,
    output [31:0] RD1,
    output [31:0] RD2,
    output [31:0] ImmExt,
    output [31:0] srcb,
    output [31:0] ALUResult,
    output [31:0] read_data,
    output [31:0] jal_sonuc,
    output [31:0] branch_sonuc,
    output [31:0] pcnext,
    output [31:0] sraresult,
    output SraSrc,
    output [31:0] resultwd_son);

    pc p1(pcnext,clk,pc);
    instr_mem i1(pc,instr);
    control_unit c1(instr[6:0],instr[14:12],instr[30],Zero,PCSrc,ResultSrc,MemWrite,ALUControl,ALUSrc,ImmSrc,RegWrite,SraSrc);
    reg_file r1(instr[19:15],instr[24:20],instr[11:7],resultwd_son,RegWrite,clk,RD1,RD2);
    extend e1(ImmSrc,instr[31:7],ImmExt);
    mux_2x1 m1(RD2,ImmExt,ALUSrc,srcb);
    ALU a1(RD1,srcb,ALUControl,Zero,ALUResult);
    data_memr d1(ALUResult,RD2,clk,MemWrite,read_data);
    mux_3 m2(ALUResult,read_data,jal_sonuc,ResultSrc,resultwd);
    adder_jal a11(pc,jal_sonuc);
    adder_branch a12(pc,ImmExt,branch_sonuc);
    mux_2x1 m3(jal_sonuc,branch_sonuc,PCSrc,pcnext);
    shift_right_arithmetic s1(RD1,RD2[4:0],sraresult);
    mux_2x1 m4(resultwd,sraresult,SraSrc,resultwd_son);

endmodule

sra added/s2_tb.v
`include "s2.v"

module stest;
    reg clk, rst;
    wire [31:0] pc,instr;
    wire Zero;
    wire PCSrc;
    wire [1:0] ResultSrc;
    wire MemWrite;
    wire [2:0] ALUControl;
    wire ALUSrc;
    wire [1:0] ImmSrc;
    wire RegWrite;
    wire [31:0] resultwd;
    wire [31:0] RD1;
    wire [31:0] RD2;
    wire [31:0] ImmExt;
    wire [31:0] srcb;
    wire [31:0] ALUResult;
    wire [31:0] read_data;
    wire [31:0] jal_sonuc;
    wire [31:0] branch_sonuc;
    wire [31:0] pcnext;
    wire [31:0] sraresult;
    wire SraSrc;
    wire [31:0] resultwd_son;
    
    asd a1(clk,rst,pc,instr,Zero,PCSrc,ResultSrc,MemWrite,ALUControl,ALUSrc,ImmSrc,RegWrite,resultwd,RD1,RD2,ImmExt,srcb,ALUResult,read_data,jal_sonuc,branch_sonuc,pcnext,sraresult,SraSrc,resultwd_son);

    initial begin
        clk = 0;
        forever #5 clk = ~clk;
    end
    initial begin
        #255;
        $finish;
    end

    initial begin
            $dumpfile("s2_vcd.vcd");
            $dumpvars(0, stest);
    end
endmodule

sra added/s2_vcd.vcd
$date
	Sun Apr 28 13:23:55 2024
$end
$version
	Icarus Verilog
$end
$timescale
	1s
$end
$scope module stest $end
$var wire 32 ! srcb [31:0] $end
$var wire 32 " sraresult [31:0] $end
$var wire 32 # resultwd_son [31:0] $end
$var wire 32 $ resultwd [31:0] $end
$var wire 32 % read_data [31:0] $end
$var wire 32 & pcnext [31:0] $end
$var wire 32 ' pc [31:0] $end
$var wire 32 ( jal_sonuc [31:0] $end
$var wire 32 ) instr [31:0] $end
$var wire 32 * branch_sonuc [31:0] $end
$var wire 1 + Zero $end
$var wire 1 , SraSrc $end
$var wire 2 - ResultSrc [1:0] $end
$var wire 1 . RegWrite $end
$var wire 32 / RD2 [31:0] $end
$var wire 32 0 RD1 [31:0] $end
$var wire 1 1 PCSrc $end
$var wire 1 2 MemWrite $end
$var wire 2 3 ImmSrc [1:0] $end
$var wire 32 4 ImmExt [31:0] $end
$var wire 1 5 ALUSrc $end
$var wire 32 6 ALUResult [31:0] $end
$var wire 3 7 ALUControl [2:0] $end
$var reg 1 8 clk $end
$var reg 1 9 rst $end
$scope module a1 $end
$var wire 1 8 clk $end
$var wire 1 9 reset $end
$var wire 32 : srcb [31:0] $end
$var wire 32 ; sraresult [31:0] $end
$var wire 32 < resultwd_son [31:0] $end
$var wire 32 = resultwd [31:0] $end
$var wire 32 > read_data [31:0] $end
$var wire 32 ? pcnext [31:0] $end
$var wire 32 @ pc [31:0] $end
$var wire 32 A jal_sonuc [31:0] $end
$var wire 32 B instr [31:0] $end
$var wire 32 C branch_sonuc [31:0] $end
$var wire 1 + Zero $end
$var wire 1 , SraSrc $end
$var wire 2 D ResultSrc [1:0] $end
$var wire 1 . RegWrite $end
$var wire 32 E RD2 [31:0] $end
$var wire 32 F RD1 [31:0] $end
$var wire 1 1 PCSrc $end
$var wire 1 2 MemWrite $end
$var wire 2 G ImmSrc [1:0] $end
$var wire 32 H ImmExt [31:0] $end
$var wire 1 5 ALUSrc $end
$var wire 32 I ALUResult [31:0] $end
$var wire 3 J ALUControl [2:0] $end
$scope module a1 $end
$var wire 1 + Zero $end
$var wire 32 K SrcB [31:0] $end
$var wire 32 L SrcA [31:0] $end
$var wire 3 M ALUControl [2:0] $end
$var reg 32 N ALUResult [31:0] $end
$upscope $end
$scope module a11 $end
$var wire 32 O PCPlus4 [31:0] $end
$var wire 32 P PC [31:0] $end
$upscope $end
$scope module a12 $end
$var wire 32 Q PCTarget [31:0] $end
$var wire 32 R PC [31:0] $end
$var wire 32 S ImmExt [31:0] $end
$upscope $end
$scope module c1 $end
$var wire 1 1 PCSrc $end
$var wire 1 + Zero $end
$var wire 3 T funct3 [2:0] $end
$var wire 1 U funct7_5 $end
$var wire 7 V op [6:0] $end
$var wire 1 W jump $end
$var wire 1 X branch $end
$var wire 1 , SraSrc $end
$var wire 2 Y ResultSrc [1:0] $end
$var wire 1 . RegWrite $end
$var wire 1 2 MemWrite $end
$var wire 2 Z ImmSrc [1:0] $end
$var wire 1 5 ALUSrc $end
$var wire 2 [ ALUOp [1:0] $end
$var wire 3 \ ALUControl [2:0] $end
$scope module ALU_dec $end
$var wire 3 ] funct3 [2:0] $end
$var wire 1 U funct7_5 $end
$var wire 1 ^ op5 $end
$var wire 2 _ ALUOp [1:0] $end
$var reg 3 ` ALUControl [2:0] $end
$upscope $end
$scope module main_dec $end
$var wire 3 a funct3 [2:0] $end
$var wire 1 U funct7_5 $end
$var wire 7 b op [6:0] $end
$var wire 1 W jump $end
$var wire 1 X branch $end
$var wire 1 , SraSrc $end
$var wire 2 c ResultSrc [1:0] $end
$var wire 1 . RegWrite $end
$var wire 1 2 MemWrite $end
$var wire 2 d ImmSrc [1:0] $end
$var wire 1 5 ALUSrc $end
$var wire 2 e ALUOp [1:0] $end
$var reg 12 f controls [11:0] $end
$upscope $end
$upscope $end
$scope module d1 $end
$var wire 32 g a_enter [31:0] $end
$var wire 1 8 clk $end
$var wire 32 h read_data [31:0] $end
$var wire 1 2 write_en $end
$var wire 32 i write_data [31:0] $end
$var integer 32 j i [31:0] $end
$upscope $end
$scope module e1 $end
$var wire 2 k ImmSrc [1:0] $end
$var wire 25 l instruction [31:7] $end
$var reg 32 m ImmExt [31:0] $end
$upscope $end
$scope module i1 $end
$var wire 32 n addr_instr [31:0] $end
$var reg 32 o rd_instr [31:0] $end
$upscope $end
$scope module m1 $end
$var wire 32 p data1 [31:0] $end
$var wire 1 5 sel $end
$var wire 32 q out [31:0] $end
$var wire 32 r data0 [31:0] $end
$upscope $end
$scope module m2 $end
$var wire 32 s a [31:0] $end
$var wire 32 t b [31:0] $end
$var wire 32 u c [31:0] $end
$var wire 2 v sel [1:0] $end
$var reg 32 w y [31:0] $end
$upscope $end
$scope module m3 $end
$var wire 32 x data0 [31:0] $end
$var wire 32 y data1 [31:0] $end
$var wire 1 1 sel $end
$var wire 32 z out [31:0] $end
$upscope $end
$scope module m4 $end
$var wire 32 { data0 [31:0] $end
$var wire 1 , sel $end
$var wire 32 | out [31:0] $end
$var wire 32 } data1 [31:0] $end
$upscope $end
$scope module p1 $end
$var wire 32 ~ PCNext [31:0] $end
$var wire 1 8 clk $end
$var reg 32 !" PC_cur [31:0] $end
$upscope $end
$scope module r1 $end
$var wire 5 "" R1 [4:0] $end
$var wire 5 #" R2 [4:0] $end
$var wire 32 $" RD1 [31:0] $end
$var wire 32 %" RD2 [31:0] $end
$var wire 1 . RegWrite $end
$var wire 5 &" W1 [4:0] $end
$var wire 32 '" WD1 [31:0] $end
$var wire 1 8 clk $end
$var integer 32 (" i [31:0] $end
$upscope $end
$scope module s1 $end
$var wire 32 )" data_in [31:0] $end
$var wire 5 *" shift_amount [4:0] $end
$var reg 32 +" result [31:0] $end
$upscope $end
$upscope $end
$upscope $end
$enddefinitions $end
$comment Show the parameter values. $end
$dumpall
$end
#0
$dumpvars
b0 +"
b0 *"
b0 )"
b100000 ("
b11 '"
b1 &"
b0 %"
b0 $"
b11 #"
b0 ""
b0 !"
b100 ~
b0 }
b11 |
b11 {
b100 z
b11 y
b100 x
b11 w
b0 v
b100 u
b0 t
b11 s
b0 r
b11 q
b11 p
b1100000000000010010011 o
b0 n
b11 m
b110000000000001 l
b0 k
b1000000 j
b0 i
b0 h
b11 g
b10010000100 f
b10 e
b0 d
b0 c
b10011 b
b0 a
b0 `
b10 _
0^
b0 ]
b0 \
b10 [
b0 Z
b0 Y
0X
0W
b10011 V
0U
b0 T
b11 S
b0 R
b11 Q
b0 P
b100 O
b11 N
b0 M
b0 L
b11 K
b0 J
b11 I
b11 H
b0 G
b0 F
b0 E
b0 D
b11 C
b1100000000000010010011 B
b100 A
b0 @
b100 ?
b0 >
b11 =
b11 <
b0 ;
b11 :
x9
08
b0 7
b11 6
15
b11 4
b0 3
02
01
b0 0
b0 /
1.
b0 -
0,
0+
b11 *
b1100000000000010010011 )
b100 (
b0 '
b100 &
b0 %
b11 $
b11 #
b0 "
b11 !
$end
#5
b11 "
b11 ;
b11 }
b11 +"
b1000 #
b1000 <
b1000 |
b1000 '"
b101 !
b101 :
b101 K
b101 q
b1000 $
b1000 =
b1000 w
b1000 {
b101 4
b101 H
b101 S
b101 m
b101 p
b1000 6
b1000 I
b1000 N
b1000 g
b1000 s
b1010000100000010 l
b10 &"
b101 #"
b11 0
b11 F
b11 L
b11 $"
b11 )"
b1 ""
b1000 &
b1000 ?
b1000 z
b1000 ~
b10100001000000100010011 )
b10100001000000100010011 B
b10100001000000100010011 o
b1001 *
b1001 C
b1001 Q
b1001 y
b1000 (
b1000 A
b1000 O
b1000 u
b1000 x
b100 '
b100 @
b100 P
b100 R
b100 n
b100 !"
18
#10
08
#15
bx 3
bx G
bx Z
bx d
bx k
05
b1 "
b1 ;
b1 }
b1 +"
b1xx00000100 f
b0 %
b0 >
b0 h
b0 t
b101 #
b101 <
b101 |
b101 '"
b11 !
b11 :
b11 K
b11 q
b101 $
b101 =
b101 w
b101 {
bx 4
bx H
bx S
bx m
bx p
b11 *"
b101 6
b101 I
b101 N
b101 g
b101 s
b1 7
b1 J
b1 M
b1 \
b1 `
1^
b100000000010001000000100 l
b100 &"
b11 /
b11 E
b11 i
b11 r
b11 %"
b1 #"
b1000 0
b1000 F
b1000 L
b1000 $"
b1000 )"
b10 ""
1U
b110011 V
b110011 b
b1100 &
b1100 ?
b1100 z
b1100 ~
b1000000000100010000001000110011 )
b1000000000100010000001000110011 B
b1000000000100010000001000110011 o
bx *
bx C
bx Q
bx y
b1100 (
b1100 A
b1100 O
b1100 u
b1100 x
b1000 '
b1000 @
b1000 P
b1000 R
b1000 n
b1000 !"
18
#20
08
#25
b0 "
b0 ;
b0 }
b0 +"
b111 #
b111 <
b111 |
b111 '"
b111 $
b111 =
b111 w
b111 {
b101 !
b101 :
b101 K
b101 q
b101 *"
b111 6
b111 I
b111 N
b111 g
b111 s
b11 7
b11 J
b11 M
b11 \
b11 `
b1000000111000101 l
b101 &"
b101 /
b101 E
b101 i
b101 r
b101 %"
b100 #"
b11 0
b11 F
b11 L
b11 $"
b11 )"
b1 ""
0U
b110 T
b110 ]
b110 a
b10000 &
b10000 ?
b10000 z
b10000 ~
b10000001110001010110011 )
b10000001110001010110011 B
b10000001110001010110011 o
b10000 (
b10000 A
b10000 O
b10000 u
b10000 x
b1100 '
b1100 @
b1100 P
b1100 R
b1100 n
b1100 !"
18
#30
08
#35
0+
b0 %
b0 >
b0 h
b0 t
b11000 *
b11000 C
b11000 Q
b11000 y
b1000 4
b1000 H
b1000 S
b1000 m
b1000 p
0.
b1 3
b1 G
b1 Z
b1 d
b1 k
15
12
bx -
bx D
bx Y
bx c
bx v
b0 [
b0 _
b0 e
b111xx0000 f
bx #
bx <
bx |
bx '"
bx $
bx =
bx w
bx {
b1011 6
b1011 I
b1011 N
b1011 g
b1011 s
b1000 !
b1000 :
b1000 K
b1000 q
b111 *"
b0 7
b0 J
b0 M
b0 \
b0 `
b1010000101001000 l
b1000 &"
b111 /
b111 E
b111 i
b111 r
b111 %"
b101 #"
b10 T
b10 ]
b10 a
b100011 V
b100011 b
b10100 &
b10100 ?
b10100 z
b10100 ~
b10100001010010000100011 )
b10100001010010000100011 B
b10100001010010000100011 o
b10100 (
b10100 A
b10100 O
b10100 u
b10100 x
b10000 '
b10000 @
b10000 P
b10000 R
b10000 n
b10000 !"
18
#40
08
#45
b111 #
b111 <
b111 |
b111 '"
b111 $
b111 =
b111 w
b111 {
1.
b0 3
b0 G
b0 Z
b0 d
b0 k
02
b1 -
b1 D
b1 Y
b1 c
b1 v
b11 "
b11 ;
b11 }
b11 +"
b10010010000 f
b1011 6
b1011 I
b1011 N
b1011 g
b1011 s
b1000 !
b1000 :
b1000 K
b1000 q
b1000 4
b1000 H
b1000 S
b1000 m
b1000 p
b0 *"
0^
b10000000101000011 l
b11 &"
b0 /
b0 E
b0 i
b0 r
b0 %"
b1000 #"
b11 V
b11 b
b11000 &
b11000 ?
b11000 z
b11000 ~
b100000001010000110000011 )
b100000001010000110000011 B
b100000001010000110000011 o
b11100 *
b11100 C
b11100 Q
b11100 y
b11000 (
b11000 A
b11000 O
b11000 u
b11000 x
b10100 '
b10100 @
b10100 P
b10100 R
b10100 n
b10100 !"
b111 %
b111 >
b111 h
b111 t
18
#50
08
#55
bx 3
bx G
bx Z
bx d
bx k
05
b0 -
b0 D
b0 Y
b0 c
b0 v
b10 [
b10 _
b10 e
b0 "
b0 ;
b0 }
b0 +"
b1xx00000100 f
b1110 #
b1110 <
b1110 |
b1110 '"
b111 !
b111 :
b111 K
b111 q
b1110 $
b1110 =
b1110 w
b1110 {
bx 4
bx H
bx S
bx m
bx p
b111 *"
b0 %
b0 >
b0 h
b0 t
b1110 6
b1110 I
b1110 N
b1110 g
b1110 s
1^
b1010001100000110 l
b110 &"
b111 /
b111 E
b111 i
b111 r
b111 %"
b101 #"
b111 0
b111 F
b111 L
b111 $"
b111 )"
b11 ""
b0 T
b0 ]
b0 a
b110011 V
b110011 b
b11100 &
b11100 ?
b11100 z
b11100 ~
b10100011000001100110011 )
b10100011000001100110011 B
b10100011000001100110011 o
bx *
bx C
bx Q
bx y
b11100 (
b11100 A
b11100 O
b11100 u
b11100 x
b11000 '
b11000 @
b11000 P
b11000 R
b11000 n
b11000 !"
18
#60
08
#65
b10110 #
b10110 <
b10110 |
b10110 '"
b10110 $
b10110 =
b10110 w
b10110 {
b1000 !
b1000 :
b1000 K
b1000 q
b1000 *"
b10110 6
b10110 I
b10110 N
b10110 g
b10110 s
b100011000000111 l
b111 &"
b1000 /
b1000 E
b1000 i
b1000 r
b1000 %"
b10 #"
b1110 0
b1110 F
b1110 L
b1110 $"
b1110 )"
b110 ""
b100000 &
b100000 ?
b100000 z
b100000 ~
b1000110000001110110011 )
b1000110000001110110011 B
b1000110000001110110011 o
b100000 (
b100000 A
b100000 O
b100000 u
b100000 x
b11100 '
b11100 @
b11100 P
b11100 R
b11100 n
b11100 !"
18
#70
08
#75
b110 #
b110 <
b110 |
b110 '"
0+
b110 $
b110 =
b110 w
b110 {
b1110 !
b1110 :
b1110 K
b1110 q
b1110 *"
b110 6
b110 I
b110 N
b110 g
b110 s
b10 7
b10 J
b10 M
b10 \
b10 `
b1100011111100011 l
b11 &"
b1110 /
b1110 E
b1110 i
b1110 r
b1110 %"
b110 #"
b10110 0
b10110 F
b10110 L
b10110 $"
b10110 )"
b111 ""
b111 T
b111 ]
b111 a
b100100 &
b100100 ?
b100100 z
b100100 ~
b11000111111000110110011 )
b11000111111000110110011 B
b11000111111000110110011 o
b100100 (
b100100 A
b100100 O
b100100 u
b100100 x
b100000 '
b100000 @
b100000 P
b100000 R
b100000 n
b100000 !"
18
#80
08
#85
11
b101100 *
b101100 C
b101100 Q
b101100 y
b1000 4
b1000 H
b1000 S
b1000 m
b1000 p
0.
b10 3
b10 G
b10 Z
b10 d
b10 k
bx -
bx D
bx Y
bx c
bx v
1X
b1 [
b1 _
b1 e
b1000xx1010 f
bx #
bx <
bx |
bx '"
1+
bx $
bx =
bx w
bx {
b111 !
b111 :
b111 K
b111 q
b111 *"
b0 %
b0 >
b0 h
b0 t
b0 6
b0 I
b0 N
b0 g
b0 s
b1 7
b1 J
b1 M
b1 \
b1 `
b1010010100101000 l
b1000 &"
b111 /
b111 E
b111 i
b111 r
b111 %"
b101 #"
b111 0
b111 F
b111 L
b111 $"
b111 )"
b101 ""
b1 T
b1 ]
b1 a
b1100011 V
b1100011 b
b101100 &
b101100 ?
b101100 z
b101100 ~
b10100101001010001100011 )
b10100101001010001100011 B
b10100101001010001100011 o
b101000 (
b101000 A
b101000 O
b101000 u
b101000 x
b100100 '
b100100 @
b100100 P
b100100 R
b100100 n
b100100 !"
18
#90
08
#95
01
0+
b1000 !
b1000 :
b1000 K
b1000 q
b1000 *"
bx %
bx >
bx h
bx t
b11111111111111111111111111111110 6
b11111111111111111111111111111110 I
b11111111111111111111111111111110 N
b11111111111111111111111111111110 g
b11111111111111111111111111111110 s
b100001100101000 l
b1000 /
b1000 E
b1000 i
b1000 r
b1000 %"
b10 #"
b110 0
b110 F
b110 L
b110 $"
b110 )"
b11 ""
b110000 &
b110000 ?
b110000 z
b110000 ~
b1000011001010001100011 )
b1000011001010001100011 B
b1000011001010001100011 o
b110100 *
b110100 C
b110100 Q
b110100 y
b110000 (
b110000 A
b110000 O
b110000 u
b110000 x
b101100 '
b101100 @
b101100 P
b101100 R
b101100 n
b101100 !"
18
#100
08
#105
b1 #
b1 <
b1 |
b1 '"
bx 4
bx H
bx S
bx m
bx p
b1 $
b1 =
b1 w
b1 {
b101 7
b101 J
b101 M
b101 \
b101 `
1.
bx 3
bx G
bx Z
bx d
bx k
b0 -
b0 D
b0 Y
b0 c
b0 v
0X
b10 [
b10 _
b10 e
b1xx00000100 f
01
0+
b1110 !
b1110 :
b1110 K
b1110 q
b1110 *"
b0 %
b0 >
b0 h
b0 t
b1 6
b1 I
b1 N
b1 g
b1 s
b1100001001001000 l
b1110 /
b1110 E
b1110 i
b1110 r
b1110 %"
b110 #"
b1000 0
b1000 F
b1000 L
b1000 $"
b1000 )"
b10 ""
b10 T
b10 ]
b10 a
b110011 V
b110011 b
b110100 &
b110100 ?
b110100 z
b110100 ~
b11000010010010000110011 )
b11000010010010000110011 B
b11000010010010000110011 o
bx *
bx C
bx Q
bx y
b110100 (
b110100 A
b110100 O
b110100 u
b110100 x
b110000 '
b110000 @
b110000 P
b110000 R
b110000 n
b110000 !"
18
#110
08
#115
b0 %
b0 >
b0 h
b0 t
b111110 *
b111110 C
b111110 Q
b111110 y
b1010 4
b1010 H
b1010 S
b1010 m
b1010 p
b0 3
b0 G
b0 Z
b0 d
b0 k
15
b10110 "
b10110 ;
b10110 }
b10110 +"
b10010000100 f
b11110 #
b11110 <
b11110 |
b11110 '"
b11110 $
b11110 =
b11110 w
b11110 {
b1010 !
b1010 :
b1010 K
b1010 q
b0 *"
b11110 6
b11110 I
b11110 N
b11110 g
b11110 s
b11 7
b11 J
b11 M
b11 \
b11 `
0^
b10100011111000100 l
b100 &"
b0 /
b0 E
b0 i
b0 r
b0 %"
b1010 #"
b10110 0
b10110 F
b10110 L
b10110 $"
b10110 )"
b111 ""
b110 T
b110 ]
b110 a
b10011 V
b10011 b
b111000 &
b111000 ?
b111000 z
b111000 ~
b101000111110001000010011 )
b101000111110001000010011 B
b101000111110001000010011 o
b111000 (
b111000 A
b111000 O
b111000 u
b111000 x
b110100 '
b110100 @
b110100 P
b110100 R
b110100 n
b110100 !"
18
#120
08
#125
b11110 "
b11110 ;
b11110 }
b11110 +"
b10000 #
b10000 <
b10000 |
b10000 '"
b10001 !
b10001 :
b10001 K
b10001 q
b10000 $
b10000 =
b10000 w
b10000 {
b10001 4
b10001 H
b10001 S
b10001 m
b10001 p
b10000 6
b10000 I
b10000 N
b10000 g
b10000 s
b10 7
b10 J
b10 M
b10 \
b10 `
b100010010011100011 l
b11 &"
b10001 #"
b11110 0
b11110 F
b11110 L
b11110 $"
b11110 )"
b100 ""
b111 T
b111 ]
b111 a
b111100 &
b111100 ?
b111100 z
b111100 ~
b1000100100111000110010011 )
b1000100100111000110010011 B
b1000100100111000110010011 o
b1001001 *
b1001001 C
b1001001 Q
b1001001 y
b111100 (
b111100 A
b111100 O
b111100 u
b111100 x
b111000 '
b111000 @
b111000 P
b111000 R
b111000 n
b111000 !"
18
#130
08
#135
b0 #
b0 <
b0 |
b0 '"
1+
b0 $
b0 =
b0 w
b0 {
b11101 !
b11101 :
b11101 K
b11101 q
b0 6
b0 I
b0 N
b0 g
b0 s
b11101 4
b11101 H
b11101 S
b11101 m
b11101 p
b101 7
b101 J
b101 M
b101 \
b101 `
b111010010001001001 l
b1001 &"
b11101 #"
b10 T
b10 ]
b10 a
b1000000 &
b1000000 ?
b1000000 z
b1000000 ~
b1110100100010010010010011 )
b1110100100010010010010011 B
b1110100100010010010010011 o
b1011001 *
b1011001 C
b1011001 Q
b1011001 y
b1000000 (
b1000000 A
b1000000 O
b1000000 u
b1000000 x
b111100 '
b111100 @
b111100 P
b111100 R
b111100 n
b111100 !"
18
#140
08
